langchain_baseten-0.1.9.dist-info/METADATA
langchain_baseten-0.1.9.dist-info/WHEEL
langchain_baseten-0.1.9.dist-info/entry_points.txt
langchain_baseten-0.1.9.dist-info/licenses/LICENSE
langchain_baseten/__init__.py
langchain_baseten/chat_models.py
langchain_baseten/embeddings.py
langchain_baseten/py.typed
langchain_baseten-0.1.9.dist-info/RECORD
