Metadata-Version: 2.1
Name: langchain-baseten
Version: 0.1.9
Summary: An integration package connecting Baseten and LangChain
License: MIT
Project-URL: Source Code, https://github.com/basetenlabs/langchain-baseten/tree/master/libs/baseten
Project-URL: Release Notes, https://github.com/langchain-ai/langchain/releases?q=tag%3A%22langchain-baseten%3D%3D0%22&expanded=true
Project-URL: repository, https://github.com/langchain-ai/langchain
Requires-Python: <4.0.0,>=3.9.0
Requires-Dist: langchain-core<2.0.0,>=0.3.55
Requires-Dist: openai<3.0.0,>=2.4.0
Requires-Dist: baseten-performance-client>=0.0.11
